rich_tree_cli/__init__.py
rich_tree_cli/_args.py
rich_tree_cli/_get_console.py
rich_tree_cli/_models.py
rich_tree_cli/constants.py
rich_tree_cli/file_info.py
rich_tree_cli/ignore_handler.py
rich_tree_cli/main.py
rich_tree_cli/output_manager.py
rich_tree_cli/export/__init__.py
rich_tree_cli/export/_common.py
rich_tree_cli/export/as_html.py
rich_tree_cli/export/as_json.py
rich_tree_cli/export/as_toml.py
rich_tree_cli/export/as_xml.py
rich_tree_cli/export/icons.py
rich_tree_cli/export/html/__init__.py
rich_tree_cli/export/html/html_template.py
rich_tree_cli/export/html/assets/styles.css
rich_tree_cli/export/html/assets/template.jinja2
rich_tree_cli/export/html/assets/icons/claude.svg
rich_tree_cli/export/html/assets/icons/css.svg
rich_tree_cli/export/html/assets/icons/db.svg
rich_tree_cli/export/html/assets/icons/env.svg
rich_tree_cli/export/html/assets/icons/file.svg
rich_tree_cli/export/html/assets/icons/folder.svg
rich_tree_cli/export/html/assets/icons/git.svg
rich_tree_cli/export/html/assets/icons/html.svg
rich_tree_cli/export/html/assets/icons/javascript.svg
rich_tree_cli/export/html/assets/icons/json.svg
rich_tree_cli/export/html/assets/icons/log.svg
rich_tree_cli/export/html/assets/icons/markdown.svg
rich_tree_cli/export/html/assets/icons/nix.svg
rich_tree_cli/export/html/assets/icons/python.svg
rich_tree_cli/export/html/assets/icons/settings.svg
rich_tree_cli/export/html/assets/icons/src.svg
rich_tree_cli/export/html/assets/icons/svg.svg
rich_tree_cli/export/html/assets/icons/symlink.svg
rich_tree_cli/export/html/assets/icons/tests.svg
rich_tree_cli/export/html/assets/icons/toml.svg
rich_tree_cli/export/html/assets/icons/txt.svg
rich_tree_cli/export/html/assets/icons/vscode.svg
rich_tree_cli-0.4.0.dist-info/METADATA
rich_tree_cli-0.4.0.dist-info/WHEEL
rich_tree_cli-0.4.0.dist-info/entry_points.txt
rich_tree_cli-0.4.0.dist-info/RECORD
