Metadata-Version: 2.4
Name: rich-tree-cli
Version: 0.4.0
Summary: A command-line interface for visualizing directory trees with rich formatting and various options.
Author-email: chaz <bright.lid5647@fastmail.com>
Requires-Python: >=3.11
Requires-Dist: bear-epoch-time>=1.2.10
Requires-Dist: defusedxml>=0.7.1
Requires-Dist: jinja2>=3.1.6
Requires-Dist: pathspec>=0.12.1
Requires-Dist: rich>=14.0.0
Requires-Dist: tomli-w>=1.2.0
